Metadata-Version: 1.1
Name: regcomsrv
Version: 1.0.3
Summary: Package regcomsrv helps you to register or unregister COM-servers that defined in python packages
Home-page: https://github.com/vowatchka/regcomsrv
Author: Vladimir Saltykov
Author-email: vowatchka@mail.ru
License: MIT
Keywords: regcomsrv registration unregistration register unregister com server
Platform: UNKNOWN
Classifier: Development Status :: 5 - Production/Stable
Classifier: Intended Audience :: Developers
Classifier: License :: OSI Approved :: MIT License
Classifier: Operating System :: OS Independent
Classifier: Programming Language :: Python :: 3
Classifier: Programming Language :: Python :: 3.5
Classifier: Programming Language :: Python :: 3.6
Classifier: Programming Language :: Python :: 3.7
Classifier: Topic :: Software Development :: Libraries :: Python Modules
Classifier: Topic :: Utilities
